unbapi/__init__.py
unbapi/application.py
unbapi/exceptions.py
unbapi/guild.py
unbapi/items.py
unbapi/user.py
unbapi-0.1.0.dist-info/LICENSE
unbapi-0.1.0.dist-info/METADATA
unbapi-0.1.0.dist-info/WHEEL
unbapi-0.1.0.dist-info/top_level.txt
unbapi-0.1.0.dist-info/RECORD
