Metadata-Version: 2.1
Name: unbapi
Version: 0.1.0
Summary: API wrapper for the UnbelievaBoat Discord bot in Python
Home-page: https://github.com/TreeBen77/unb-api-py
Author: TreeBen77
License: MIT
Requires-Python: >=3.9.0
License-File: LICENSE
Requires-Dist: requests
